{
  "login_200":[
    {
      "id": "shirakurak",
      "name": "白倉K",
      "password": "P@ssw0rd"
    }
  ],
  "login_401":[
    {
      "id": "null",
      "name": "null",
      "password": "null"
    }
  ],
  "dogs":[
   {
      "img": "dog1",
      "name": "ケルベロス",
      "area": "群馬"
    },
    {
      "img": "dog2",
      "name": "チワワ",
      "area": "大阪"
    },
    {
      "img": "dog3",
      "name": "ハチ公",
      "area": "東京"
    },
    {
      "img": "dog4",
      "name": "パトラッシュ",
      "area": "北海道"
    },
    {
      "img": "dog5",
      "name": "いらすとや１",
      "area": "佐賀"
    },
    {
      "img": "dog6",
      "name": "いらすとや２",
      "area": "福井"
    },
   {
      "img": "dog1",
      "name": "ケルベロス",
      "area": "群馬"
    },
    {
      "img": "dog2",
      "name": "チワワ",
      "area": "大阪"
    },
    {
      "img": "dog3",
      "name": "ハチ公",
      "area": "東京"
    },
    {
      "img": "dog4",
      "name": "パトラッシュ",
      "area": "北海道"
    },
    {
      "img": "dog5",
      "name": "いらすとや１",
      "area": "佐賀"
    },
    {
      "img": "dog6",
      "name": "いらすとや２",
      "area": "福井"
    },
    {
      "img": "dog1",
      "name": "ケルベロス",
      "area": "群馬"
    },
    {
      "img": "dog2",
      "name": "チワワ",
      "area": "大阪"
    },
    {
      "img": "dog3",
      "name": "ハチ公",
      "area": "東京"
    },
    {
      "img": "dog4",
      "name": "パトラッシュ",
      "area": "北海道"
    },
    {
      "img": "dog5",
      "name": "いらすとや１",
      "area": "佐賀"
    },
    {
      "img": "dog6",
      "name": "いらすとや２",
      "area": "福井"
    },
    {
      "img": "dog1",
      "name": "ケルベロス",
      "area": "群馬"
    },
    {
      "img": "dog2",
      "name": "チワワ",
      "area": "大阪"
    },
    {
      "img": "dog3",
      "name": "ハチ公",
      "area": "東京"
    },
    {
      "img": "dog4",
      "name": "パトラッシュ",
      "area": "北海道"
    },
    {
      "img": "dog5",
      "name": "いらすとや１",
      "area": "佐賀"
    },
    {
      "img": "dog6",
      "name": "いらすとや２",
      "area": "福井"
    },
    {
      "img": "dog1",
      "name": "ケルベロス",
      "area": "群馬"
    },
    {
      "img": "dog2",
      "name": "チワワ",
      "area": "大阪"
    },
    {
      "img": "dog3",
      "name": "ハチ公",
      "area": "東京"
    },
    {
      "img": "dog4",
      "name": "パトラッシュ",
      "area": "北海道"
    },
    {
      "img": "dog5",
      "name": "いらすとや１",
      "area": "佐賀"
    },
    {
      "img": "dog6",
      "name": "いらすとや２",
      "area": "福井"
    },
    {
      "img": "dog1",
      "name": "ケルベロス",
      "area": "群馬"
    },
    {
      "img": "dog2",
      "name": "チワワ",
      "area": "大阪"
    },
    {
      "img": "dog3",
      "name": "ハチ公",
      "area": "東京"
    },
    {
      "img": "dog4",
      "name": "パトラッシュ",
      "area": "北海道"
    },
    {
      "img": "dog5",
      "name": "いらすとや１",
      "area": "佐賀"
    },
    {
      "img": "dog6",
      "name": "いらすとや２",
      "area": "福井"
    },
    {
      "img": "dog1",
      "name": "ケルベロス",
      "area": "群馬"
    },
    {
      "img": "dog2",
      "name": "チワワ",
      "area": "大阪"
    },
    {
      "img": "dog3",
      "name": "ハチ公",
      "area": "東京"
    },
    {
      "img": "dog4",
      "name": "パトラッシュ",
      "area": "北海道"
    },
    {
      "img": "dog5",
      "name": "いらすとや１",
      "area": "佐賀"
    },
    {
      "img": "dog6",
      "name": "いらすとや２",
      "area": "福井"
    }
  ]
}
